xlcompose/__init__.py
xlcompose/core.py
xlcompose/settings.yaml
xlcompose/styles.css
xlcompose/templates.py
xlcompose/test_xlc.py
xlcompose-0.3.2.dist-info/LICENSE
xlcompose-0.3.2.dist-info/METADATA
xlcompose-0.3.2.dist-info/WHEEL
xlcompose-0.3.2.dist-info/top_level.txt
xlcompose-0.3.2.dist-info/RECORD
