Metadata-Version: 2.1
Name: xlcompose
Version: 0.3.2
Summary: A declarative API for composing spreadsheets from python
Home-page: https://github.com/jbogaardt/xlcompose
Download-URL: https://github.com/jbogaardt/xlcompose/archive/v0.3.2.tar.gz
Maintainer: John Bogaardt
Maintainer-email: jbogaardt@gmail.com
License: LICENSE
License-File: LICENSE
Requires-Dist: xlsxwriter >=1.1.8
Requires-Dist: pandas
Requires-Dist: pyyaml
Requires-Dist: jinja2
